[ 
    {
        "name" : "Sajib Chandra Das",
        "email" : "abc@gmail.com",
        "links" : [
            {"facebook":"sajib" },         
            {"youtube" : "sajib2"},
            {"github":[
                "sajib581",
                [
                    "sajib121",
                    {"git":"sajib11"}
                ]
            ]}
        ],
        "skills":[
            "java",
            "node js",
            "angular js",
            "react js"
        ],
        "age" : 24,
        "isMarried":false,
        "baby" : null
    },
    {
        "name" : "Sajib Chandra Das",
        "email" : "abc@gmail.com",
        "links" : [
            {"facebook":"sajib" },         
            {"youtube" : "sajib2"},
            {"github":[
                "sajib581",
                [
                    "sajib121",
                    {"git":"sajib11"}
                ]
            ]}
        ],
        "skills":[
            "java",
            "node js",
            "angular js",
            "react js"
        ],
        "age" : 24,
        "isMarried":false,
        "baby" : null
    }
]